{
  "content/post/links/2014-08-23-link-post.md": {
    "title": "Links for August 23, 2014",
    "current_tags": [],
    "proposed_tags": ["python", "docker", "command-line-tools", "distributed-systems"]
  },
  "content/post/links/2014-08-25 sundry-links-for-August-25-2014.md": {
    "title": "Links for August 25, 2014",
    "current_tags": [],
    "proposed_tags": ["python", "command-line-tools", "stream-processing", "macos-productivity"]
  },
  "content/post/links/2014-08-28 sundry-links-for-August-28-2014.md": {
    "title": "Links for August 28, 2014",
    "current_tags": [],
    "proposed_tags": ["python", "distributed-systems", "macos-productivity", "mathematics"]
  },
  "content/post/links/2014-08-30-sundry-links-for-August-30-2014.md": {
    "title": "Links for August 30, 2014",
    "current_tags": [],
    "proposed_tags": ["python", "data-visualization", "git", "scikit-learn", "r"]
  },
  "content/post/links/2014-09-10-sundry-links-for-September-10-2014.md": {
    "title": "Links for September 10, 2014",
    "current_tags": [],
    "proposed_tags": ["python", "flask", "command-line-tools"]
  },
  "content/post/links/2014-09-20-sundry-links-for-September-20-2014.md": {
    "title": "Links for September 20, 2014",
    "current_tags": [],
    "proposed_tags": ["python", "open-source", "elasticsearch", "stream-processing", "git"]
  },
  "content/post/links/2014-09-25-sundry-links-for-September-25-2014.md": {
    "title": "Links for September 25, 2014",
    "current_tags": [],
    "proposed_tags": ["statistics", "command-line-tools", "data-visualization"]
  },
  "content/post/links/2014-09-30-sundry-links-for-September-30-2014.md": {
    "title": "Links for September 30, 2014",
    "current_tags": [],
    "proposed_tags": ["python", "apache-spark", "command-line-tools", "web-development"]
  },
  "content/post/links/2014-11-01-sundry-links-for-November-01-2014.md": {
    "title": "Links for November 1, 2014",
    "current_tags": [],
    "proposed_tags": ["python", "command-line-tools", "unicode", "bash"]
  },
  "content/post/links/2014-11-03-sundry-links-for-November-03-2014.md": {
    "title": "Links for November 3, 2014",
    "current_tags": [],
    "proposed_tags": ["python", "flask", "web-development", "open-data", "bash"]
  },
  "content/post/links/2014-11-12-sundry-links-for-November-12-2014.md": {
    "title": "Links for November 12, 2014",
    "current_tags": [],
    "proposed_tags": ["python", "apache-spark", "robotics", "mapreduce"]
  },
  "content/post/links/2014-11-17-sundry-links-for-November-17-2014.md": {
    "title": "Links for November 17, 2014",
    "current_tags": [],
    "proposed_tags": ["python", "virtualenv", "developer-tools"]
  },
  "content/post/links/2014-11-25-sundry-links-for-November-24-2014.md": {
    "title": "Links for November 24, 2014",
    "current_tags": [],
    "proposed_tags": ["machine-learning", "data-structures", "scala", "programming-books"]
  },
  "content/post/links/2014-12-04-sundry-links-for-December-04-2014.md": {
    "title": "Links for December 4, 2014",
    "current_tags": [],
    "proposed_tags": ["python", "bayesian-statistics", "scikit-learn", "recommender-systems"]
  },
  "content/post/links/2014-12-06-sundry-links-for-December-06-2014.md": {
    "title": "Links for December 6, 2014",
    "current_tags": [],
    "proposed_tags": ["linear-algebra", "geospatial", "python", "bash", "statistics"]
  },
  "content/post/links/2014-12-22-sundry-links-for-December-22-2014.md": {
    "title": "Links for December 22, 2014",
    "current_tags": [],
    "proposed_tags": ["machine-learning", "bayesian-statistics", "python", "git", "software-engineering"]
  },
  "content/post/links/2014-12-29-sundry-links-for-December-29-2014.md": {
    "title": "Links for December 29, 2014",
    "current_tags": [],
    "proposed_tags": ["python", "macos-productivity", "developer-tools"]
  },
  "content/post/links/2015-01-19-sundry-links-for-January-19-2015.md": {
    "title": "Links for January 19, 2015",
    "current_tags": [],
    "proposed_tags": ["python", "flask", "r", "macos-productivity", "office-culture"]
  },
  "content/post/links/2015-03-13-sundry-links-for-March-13-2015.md": {
    "title": "Links for March 13, 2015",
    "current_tags": [],
    "proposed_tags": ["python", "data-visualization", "matplotlib", "jupyter"]
  },
  "content/post/links/2015-03-23-sundry-links-for-March-23-2015.md": {
    "title": "Links for March 23, 2015",
    "current_tags": [],
    "proposed_tags": ["aws", "cpp", "build-tools", "mathematics"]
  }
}
